CHANGES.rst
LICENSE
MANIFEST.in
README.rst
package.json
setup.py
armstrong/__init__.py
armstrong.utils.backends.egg-info/PKG-INFO
armstrong.utils.backends.egg-info/SOURCES.txt
armstrong.utils.backends.egg-info/dependency_links.txt
armstrong.utils.backends.egg-info/namespace_packages.txt
armstrong.utils.backends.egg-info/top_level.txt
armstrong/utils/__init__.py
armstrong/utils/backends/__init__.py
armstrong/utils/backends/base.py
armstrong/utils/backends/models.py