Metadata-Version: 1.1
Name: armstrong.utils.backends
Version: 1.1.0
Summary: Generic backend system to use throughout Armstrong
Home-page: http://github.com/armstrong/armstrong.utils.backends/
Author: Bay Citizen & Texas Tribune
Author-email: dev@armstrongcms.org
License: UNKNOWN
Platform: UNKNOWN
Classifier: Development Status :: 5 - Production/Stable
Classifier: Environment :: Web Environment
Classifier: Framework :: Django
Classifier: Intended Audience :: Developers
Classifier: License :: OSI Approved :: Apache Software License
Classifier: Operating System :: OS Independent
Classifier: Programming Language :: Python
Classifier: Programming Language :: Python :: 2.6
Classifier: Programming Language :: Python :: 2.7
